<?xml version="1.0" encoding="UTF-8"?>
<beans xmlns="http://www.springframework.org/schema/beans"
    xmlns:xsi="http://www.w3.org/2001/XMLSchema-instance"
    xmlns:context="http://www.springframework.org/schema/context"
	xmlns:p="http://www.springframework.org/schema/p"
    xsi:schemaLocation="http://www.springframework.org/schema/beans
        http://www.springframework.org/schema/beans/spring-beans.xsd
        http://www.springframework.org/schema/context
        http://www.springframework.org/schema/context/spring-context.xsd">

       	
  <bean id="c1" class="step05.Computer">
  	<property name="model" value="개발용1호"/>
  	<property name="maker" value="비트컴퓨터"/>
  	<property name="options">
  		<array> <!-- 배열 값을 설정할 때 사용 -->
  			<value>USB3.0 x 3</value>
  			<value>1000GB LAN</value>
  			<value>DVD-ROM</value>
  		</array>
  	</property>
  </bean>
  
  <bean id="c2" class="step05.Computer">
  	<property name="model" value="개발용2호"/>
  	<property name="maker" value="비트컴퓨터"/>
  	<property name="options">
  		<list> <!-- 배열 값을 설정할 때 <array> 대신 <list>를 사용해도 된다. -->
  			<value>USB3.0 x 3</value>
  			<value>1000GB LAN</value>
  			<value>DVD-ROM</value>
  		</list>
  	</property> 
  </bean>

</beans>



